winpwn/__init__.py
winpwn/context.py
winpwn/dbg.py
winpwn/misc.py
winpwn/var.py
winpwn/win.py
winpwn/winpwn.py
zeropwn-0.0.4.dist-info/METADATA
zeropwn-0.0.4.dist-info/WHEEL
zeropwn-0.0.4.dist-info/top_level.txt
zeropwn-0.0.4.dist-info/RECORD
