Metadata-Version: 2.1
Name: zeropwn
Version: 0.0.4
Summary: mini pwntools for windows
Home-page: UNKNOWN
Author: byzero512
Author-email: byzero512@gamil.com
License: MIT
Platform: UNKNOWN
